{
  "dailyList": [
    {
      "avgElevation": 0,
      "avgVelocity": 34.63069904941512,
      "brakeCount": "",
      "brakeMileage": "",
      "brakeTime": "",
      "canEndTime": "2019-02-01 23:32:58",
      "canPoints": 8270,
      "canStartTime": "2019-02-01 00:23:31",
      "chargeCount": 0,
      "chargePower": 0.0,
      "city": "萍乡市",
      "clutchCount": "",
      "clutchTime": "",
      "codes": {
        "START_ENGINE_TOTAL_RUNTIME_TIME": "3893.70",
        "VB_AVG_ELEVATION": "0",
        "END_FUEL_CONSUMPTION_IDLE": "1922.00",
        "VB_CLUTCH_COUNT": "920",
        "VB_WORK_TIME": "39892",
        "ECM_START_MILEAGE": "141834270",
        "END_ENGINE_TOTAL_RUNTIME_TIME": "3904.70",
        "VB_BRAKE_COUNT": "544",
        "VB_RUN_TIME": "39892",
        "VB_BRAKE_MILEAGE": "35200",
        "CAN_BUS_START_MILEAGE": "141834250",
        "VB_ENGINE_TIME": "39892",
        "VB_MAX_VELOCITY": "110.00",
        "VB_MIN_ELEVATION": "0",
        "START_FUEL_CONSUMPTION_IDLE": "1916.50",
        "END_IDLE_TIME": "954",
        "VB_AVG_VELOCITY": "34.06",
        "VDR_END_MILEAGE": "138311780",
        "END_ENGINE_RUNTIME_TIME": "3781.95",
        "ECM_END_MILEAGE": "142222560",
        "START_IDLE_TIME": "951",
        "VDR_START_MILEAGE": "137934315",
        "VB_CLUTCH_TIME": "6930",
        "VB_IDLE_TIME": "10437",
        "VB_MIN_VELOCITY": "0.00",
        "VB_MAX_ELEVATION": "0",
        "START_ENGINE_RUNTIME_TIME": "3771.05",
        "CAN_BUS_END_MILEAGE": "142222500",
        "ERROR_GPS": "GPS定位异常",
        "VB_OFFLINE_TIME": "0",
        "VB_IDLE_FUEL_CONSUMPTION": "4.90",
        "VB_BRAKE_TIME": "5037",
        "VB_STOP_TIME": "46508"
      },
      "cycleGasConsumptionKg": "",
      "dataTime": "2019-02-01 00:00:00",
      "did": "A64838039045",
      "endCycleGasKg": "",
      "endFuel": 49227.5,
      "endGasKg": "",
      "endGasL": "",
      "endHydrogen": "",
      "endMileage": 138311780,
      "engineTime": 39239,
      "exceptions": {},
      "fuelConsumption": 137.5,
      "gasConsumptionKg": "",
      "gasConsumptionL": "",
      "gpsMileage": 0,
      "hydrogenConsumption": "",
      "id": "A64838039045",
      "idleFuelConsumption": 5.5,
      "idleTime": 10439,
      "isWork": true,
      "locationEndTime": "2019-02-01 23:32:58",
      "locationStartTime": "2019-02-01 00:24:46",
      "maxElevation": 0,
      "maxVelocity": 100.5,
      "mileage": 377465,
      "mileageSource": "VDR",
      "minElevation": 0,
      "minVelocity": 0.1,
      "offlineTimeInSeconds": 0,
      "perCycleGasConsumptionKg": "",
      "perFuelConsumption": 36.42721841760163,
      "perGasConsumptionKg": "",
      "perGasConsumptionL": "",
      "perHydrogenConsumption": "",
      "perUnchargePower": "",
      "points": 1577,
      "protocol": "ZKC02",
      "province": "江西省",
      "remark": "",
      "rowKey": "00000168a4a36c00954736fbef227a67868e8bd92d62d02d",
      "runTimeInSeconds": 39239,
      "startCycleGasKg": "",
      "startFuel": 49090.0,
      "startGasKg": "",
      "startGasL": "",
      "startHydrogen": "",
      "startMileage": 137934315,
      "stopTimeInSeconds": 47161,
      "unchargeCount": 0,
      "unchargePower": 0.0,
      "workTimeInSeconds": 39239
    },
    {
      "avgElevation": 0,
      "avgVelocity": 43.589629064763876,
      "brakeCount": "",
      "brakeMileage": "",
      "brakeTime": "",
      "canEndTime": "2019-02-02 23:32:03",
      "canPoints": 3716,
      "canStartTime": "2019-02-02 00:01:46",
      "chargeCount": 0,
      "chargePower": 0.0,
      "city": "萍乡市",
      "clutchCount": "",
      "clutchTime": "",
      "codes": {
        "START_ENGINE_TOTAL_RUNTIME_TIME": "3904.75",
        "VB_AVG_ELEVATION": "0",
        "END_FUEL_CONSUMPTION_IDLE": "1923.50",
        "VB_CLUTCH_COUNT": "407",
        "VB_WORK_TIME": "18761",
        "ECM_START_MILEAGE": "142222560",
        "END_ENGINE_TOTAL_RUNTIME_TIME": "3909.85",
        "VB_BRAKE_COUNT": "281",
        "VB_RUN_TIME": "18761",
        "VB_BRAKE_MILEAGE": "24000",
        "CAN_BUS_START_MILEAGE": "142222500",
        "VB_ENGINE_TIME": "18761",
        "VB_MAX_VELOCITY": "100.00",
        "VB_MIN_ELEVATION": "0",
        "START_FUEL_CONSUMPTION_IDLE": "1922.00",
        "END_IDLE_TIME": "955",
        "VB_AVG_VELOCITY": "42.66",
        "VDR_END_MILEAGE": "138534175",
        "END_ENGINE_RUNTIME_TIME": "3787.10",
        "ECM_END_MILEAGE": "142451185",
        "START_IDLE_TIME": "954",
        "VDR_START_MILEAGE": "138311880",
        "VB_CLUTCH_TIME": "2682",
        "VB_IDLE_TIME": "2724",
        "VB_MIN_VELOCITY": "0.00",
        "VB_MAX_ELEVATION": "0",
        "START_ENGINE_RUNTIME_TIME": "3782.00",
        "CAN_BUS_END_MILEAGE": "142451125",
        "ERROR_GPS": "GPS定位异常",
        "VB_OFFLINE_TIME": "0",
        "VB_IDLE_FUEL_CONSUMPTION": "1.30",
        "VB_BRAKE_TIME": "2764",
        "VB_STOP_TIME": "67639"
      },
      "cycleGasConsumptionKg": "",
      "dataTime": "2019-02-02 00:00:00",
      "did": "A64838039045",
      "endCycleGasKg": "",
      "endFuel": 49296.5,
      "endGasKg": "",
      "endGasL": "",
      "endHydrogen": "",
      "endMileage": 138534175,
      "engineTime": 18359,
      "exceptions": {},
      "fuelConsumption": 69.0,
      "gasConsumptionKg": "",
      "gasConsumptionL": "",
      "gpsMileage": 0,
      "hydrogenConsumption": "",
      "id": "A64838039045",
      "idleFuelConsumption": 1.5,
      "idleTime": 2700,
      "isWork": true,
      "locationEndTime": "2019-02-02 23:32:03",
      "locationStartTime": "2019-02-02 00:03:01",
      "maxElevation": 0,
      "maxVelocity": 97.5,
      "mileage": 222295,
      "mileageSource": "VDR",
      "minElevation": 0,
      "minVelocity": 0.2,
      "offlineTimeInSeconds": 0,
      "perCycleGasConsumptionKg": "",
      "perFuelConsumption": 31.039834454216244,
      "perGasConsumptionKg": "",
      "perGasConsumptionL": "",
      "perHydrogenConsumption": "",
      "perUnchargePower": "",
      "points": 797,
      "protocol": "ZKC02",
      "province": "江西省",
      "remark": "",
      "rowKey": "00000168a9c9c800954736fbef227a67868e8bd92d62d02d",
      "runTimeInSeconds": 18359,
      "startCycleGasKg": "",
      "startFuel": 49227.5,
      "startGasKg": "",
      "startGasL": "",
      "startHydrogen": "",
      "startMileage": 138311880,
      "stopTimeInSeconds": 68041,
      "unchargeCount": 0,
      "unchargePower": 0.0,
      "workTimeInSeconds": 18359
    },
    {
      "avgElevation": 0,
      "avgVelocity": 9.744790633062115,
      "brakeCount": "",
      "brakeMileage": "",
      "brakeTime": "",
      "canEndTime": "2019-02-09 23:47:21",
      "canPoints": 1454,
      "canStartTime": "2019-02-09 00:02:53",
      "chargeCount": 0,
      "chargePower": 0.0,
      "city": "萍乡市",
      "clutchCount": "",
      "clutchTime": "",
      "codes": {
        "START_ENGINE_TOTAL_RUNTIME_TIME": "3910.10",
        "VB_AVG_ELEVATION": "0",
        "END_FUEL_CONSUMPTION_IDLE": "1926.00",
        "VB_CLUTCH_COUNT": "136",
        "VB_WORK_TIME": "5053",
        "ECM_START_MILEAGE": "142451185",
        "END_ENGINE_TOTAL_RUNTIME_TIME": "3911.50",
        "VB_BRAKE_COUNT": "95",
        "VB_RUN_TIME": "5053",
        "VB_BRAKE_MILEAGE": "1900",
        "CAN_BUS_START_MILEAGE": "142451125",
        "VB_ENGINE_TIME": "5053",
        "VB_MAX_VELOCITY": "70.00",
        "VB_MIN_ELEVATION": "0",
        "START_FUEL_CONSUMPTION_IDLE": "1924.00",
        "END_IDLE_TIME": "956",
        "VB_AVG_VELOCITY": "9.72",
        "VDR_END_MILEAGE": "138547815",
        "END_ENGINE_RUNTIME_TIME": "3788.70",
        "ECM_END_MILEAGE": "142465225",
        "START_IDLE_TIME": "955",
        "VDR_START_MILEAGE": "138534175",
        "VB_CLUTCH_TIME": "1187",
        "VB_IDLE_TIME": "3052",
        "VB_MIN_VELOCITY": "0.00",
        "VB_MAX_ELEVATION": "0",
        "START_ENGINE_RUNTIME_TIME": "3787.30",
        "CAN_BUS_END_MILEAGE": "142465125",
        "ERROR_GPS": "GPS定位异常",
        "VB_OFFLINE_TIME": "0",
        "VB_IDLE_FUEL_CONSUMPTION": "2.20",
        "VB_BRAKE_TIME": "405",
        "VB_STOP_TIME": "81347"
      },
      "cycleGasConsumptionKg": "",
      "dataTime": "2019-02-09 00:00:00",
      "did": "A64838039045",
      "endCycleGasKg": "",
      "endFuel": 49307.5,
      "endGasKg": "",
      "endGasL": "",
      "endHydrogen": "",
      "endMileage": 138547815,
      "engineTime": 5039,
      "exceptions": {},
      "fuelConsumption": 9.5,
      "gasConsumptionKg": "",
      "gasConsumptionL": "",
      "gpsMileage": 0,
      "hydrogenConsumption": "",
      "id": "A64838039045",
      "idleFuelConsumption": 2.0,
      "idleTime": 2879,
      "isWork": true,
      "locationEndTime": "2019-02-09 23:47:21",
      "locationStartTime": "2019-02-09 00:04:08",
      "maxElevation": 0,
      "maxVelocity": 60.4,
      "mileage": 13640,
      "mileageSource": "VDR",
      "minElevation": 0,
      "minVelocity": 0.3,
      "offlineTimeInSeconds": 0,
      "perCycleGasConsumptionKg": "",
      "perFuelConsumption": 69.64809384164222,
      "perGasConsumptionKg": "",
      "perGasConsumptionL": "",
      "perHydrogenConsumption": "",
      "perUnchargePower": "",
      "points": 261,
      "protocol": "ZKC02",
      "province": "江西省",
      "remark": "",
      "rowKey": "00000168cdd64c00954736fbef227a67868e8bd92d62d02d",
      "runTimeInSeconds": 5039,
      "startCycleGasKg": "",
      "startFuel": 49298.0,
      "startGasKg": "",
      "startGasL": "",
      "startHydrogen": "",
      "startMileage": 138534175,
      "stopTimeInSeconds": 81361,
      "unchargeCount": 0,
      "unchargePower": 0.0,
      "workTimeInSeconds": 5039
    },
    {
      "avgElevation": 0,
      "avgVelocity": 37.7625,
      "brakeCount": "",
      "brakeMileage": "",
      "brakeTime": "",
      "canEndTime": "2019-02-10 23:55:04",
      "canPoints": 5687,
      "canStartTime": "2019-02-10 00:16:08",
      "chargeCount": 0,
      "chargePower": 0.0,
      "city": "萍乡市",
      "clutchCount": "",
      "clutchTime": "",
      "codes": {
        "START_ENGINE_TOTAL_RUNTIME_TIME": "3911.55",
        "VB_AVG_ELEVATION": "0",
        "END_FUEL_CONSUMPTION_IDLE": "1933.50",
        "VB_CLUTCH_COUNT": "358",
        "VB_WORK_TIME": "27479",
        "ECM_START_MILEAGE": "142465225",
        "END_ENGINE_TOTAL_RUNTIME_TIME": "3919.50",
        "VB_BRAKE_COUNT": "336",
        "VB_RUN_TIME": "27479",
        "VB_BRAKE_MILEAGE": "17400",
        "CAN_BUS_START_MILEAGE": "142465125",
        "VB_ENGINE_TIME": "27479",
        "VB_MAX_VELOCITY": "100.00",
        "VB_MIN_ELEVATION": "0",
        "START_FUEL_CONSUMPTION_IDLE": "1926.00",
        "END_IDLE_TIME": "958",
        "VB_AVG_VELOCITY": "39.58",
        "VDR_END_MILEAGE": "138849970",
        "END_ENGINE_RUNTIME_TIME": "3796.70",
        "ECM_END_MILEAGE": "142776000",
        "START_IDLE_TIME": "956",
        "VDR_START_MILEAGE": "138547870",
        "VB_CLUTCH_TIME": "2412",
        "VB_IDLE_TIME": "9838",
        "VB_MIN_VELOCITY": "0.00",
        "VB_MAX_ELEVATION": "0",
        "START_ENGINE_RUNTIME_TIME": "3788.70",
        "CAN_BUS_END_MILEAGE": "142776000",
        "ERROR_GPS": "GPS定位异常",
        "VB_OFFLINE_TIME": "0",
        "VB_IDLE_FUEL_CONSUMPTION": "7.40",
        "VB_BRAKE_TIME": "2386",
        "VB_STOP_TIME": "58921"
      },
      "cycleGasConsumptionKg": "",
      "dataTime": "2019-02-10 00:00:00",
      "did": "A64838039045",
      "endCycleGasKg": "",
      "endFuel": 49415.5,
      "endGasKg": "",
      "endGasL": "",
      "endHydrogen": "",
      "endMileage": 138849970,
      "engineTime": 28800,
      "exceptions": {},
      "fuelConsumption": 108.0,
      "gasConsumptionKg": "",
      "gasConsumptionL": "",
      "gpsMileage": 0,
      "hydrogenConsumption": "",
      "id": "A64838039045",
      "idleFuelConsumption": 7.5,
      "idleTime": 9360,
      "isWork": true,
      "locationEndTime": "2019-02-10 23:55:04",
      "locationStartTime": "2019-02-10 00:17:23",
      "maxElevation": 0,
      "maxVelocity": 98.5,
      "mileage": 302100,
      "mileageSource": "VDR",
      "minElevation": 0,
      "minVelocity": 0.3,
      "offlineTimeInSeconds": 0,
      "perCycleGasConsumptionKg": "",
      "perFuelConsumption": 35.749751737835155,
      "perGasConsumptionKg": "",
      "perGasConsumptionL": "",
      "perHydrogenConsumption": "",
      "perUnchargePower": "",
      "points": 1185,
      "protocol": "ZKC02",
      "province": "江西省",
      "remark": "",
      "rowKey": "00000168d2fca800954736fbef227a67868e8bd92d62d02d",
      "runTimeInSeconds": 28800,
      "startCycleGasKg": "",
      "startFuel": 49307.5,
      "startGasKg": "",
      "startGasL": "",
      "startHydrogen": "",
      "startMileage": 138547870,
      "stopTimeInSeconds": 57600,
      "unchargeCount": 0,
      "unchargePower": 0.0,
      "workTimeInSeconds": 28800
    },
    {
      "avgElevation": 0,
      "avgVelocity": 6.524242424242425,
      "brakeCount": "",
      "brakeMileage": "",
      "brakeTime": "",
      "canEndTime": "2019-02-11 23:59:37",
      "canPoints": 1705,
      "canStartTime": "2019-02-11 00:20:29",
      "chargeCount": 0,
      "chargePower": 0.0,
      "city": "萍乡市",
      "clutchCount": "",
      "clutchTime": "",
      "codes": {
        "START_ENGINE_TOTAL_RUNTIME_TIME": "3919.65",
        "VB_AVG_ELEVATION": "0",
        "END_FUEL_CONSUMPTION_IDLE": "1936.00",
        "VB_CLUTCH_COUNT": "111",
        "VB_WORK_TIME": "6253",
        "ECM_START_MILEAGE": "142776000",
        "END_ENGINE_TOTAL_RUNTIME_TIME": "3921.35",
        "VB_BRAKE_COUNT": "81",
        "VB_RUN_TIME": "6253",
        "VB_BRAKE_MILEAGE": "900",
        "CAN_BUS_START_MILEAGE": "142776000",
        "VB_ENGINE_TIME": "6253",
        "VB_MAX_VELOCITY": "60.00",
        "VB_MIN_ELEVATION": "0",
        "START_FUEL_CONSUMPTION_IDLE": "1933.50",
        "END_IDLE_TIME": "959",
        "VB_AVG_VELOCITY": "6.20",
        "VDR_END_MILEAGE": "138860740",
        "END_ENGINE_RUNTIME_TIME": "3798.40",
        "ECM_END_MILEAGE": "142786990",
        "START_IDLE_TIME": "958",
        "VDR_START_MILEAGE": "138849975",
        "VB_CLUTCH_TIME": "1608",
        "VB_IDLE_TIME": "3677",
        "VB_MIN_VELOCITY": "0.00",
        "VB_MAX_ELEVATION": "0",
        "START_ENGINE_RUNTIME_TIME": "3796.75",
        "CAN_BUS_END_MILEAGE": "142786875",
        "ERROR_GPS": "GPS定位异常",
        "VB_OFFLINE_TIME": "0",
        "VB_IDLE_FUEL_CONSUMPTION": "3.30",
        "VB_BRAKE_TIME": "478",
        "VB_STOP_TIME": "80147"
      },
      "cycleGasConsumptionKg": "",
      "dataTime": "2019-02-11 00:00:00",
      "did": "A64838039045",
      "endCycleGasKg": "",
      "endFuel": 49427.5,
      "endGasKg": "",
      "endGasL": "",
      "endHydrogen": "",
      "endMileage": 138860740,
      "engineTime": 5940,
      "exceptions": {},
      "fuelConsumption": 12.0,
      "gasConsumptionKg": "",
      "gasConsumptionL": "",
      "gpsMileage": 0,
      "hydrogenConsumption": "",
      "id": "A64838039045",
      "idleFuelConsumption": 2.5,
      "idleTime": 3239,
      "isWork": true,
      "locationEndTime": "2019-02-11 23:59:37",
      "locationStartTime": "2019-02-11 00:20:33",
      "maxElevation": 0,
      "maxVelocity": 53.9,
      "mileage": 10765,
      "mileageSource": "VDR",
      "minElevation": 0,
      "minVelocity": 0.4,
      "offlineTimeInSeconds": 0,
      "perCycleGasConsumptionKg": "",
      "perFuelConsumption": 111.4723641430562,
      "perGasConsumptionKg": "",
      "perGasConsumptionL": "",
      "perHydrogenConsumption": "",
      "perUnchargePower": "",
      "points": 331,
      "protocol": "ZKC02",
      "province": "江西省",
      "remark": "",
      "rowKey": "00000168d8230400954736fbef227a67868e8bd92d62d02d",
      "runTimeInSeconds": 5940,
      "startCycleGasKg": "",
      "startFuel": 49415.5,
      "startGasKg": "",
      "startGasL": "",
      "startHydrogen": "",
      "startMileage": 138849975,
      "stopTimeInSeconds": 80460,
      "unchargeCount": 0,
      "unchargePower": 0.0,
      "workTimeInSeconds": 5940
    },
    {
      "avgElevation": 0,
      "avgVelocity": 37.8625,
      "brakeCount": "",
      "brakeMileage": "",
      "brakeTime": "",
      "canEndTime": "2019-02-12 23:59:59",
      "canPoints": 6787,
      "canStartTime": "2019-02-12 00:28:24",
      "chargeCount": 0,
      "chargePower": 0.0,
      "city": "萍乡市",
      "clutchCount": "",
      "clutchTime": "",
      "codes": {
        "START_ENGINE_TOTAL_RUNTIME_TIME": "3921.40",
        "VB_AVG_ELEVATION": "0",
        "END_FUEL_CONSUMPTION_IDLE": "1940.00",
        "VB_CLUTCH_COUNT": "587",
        "VB_WORK_TIME": "27070",
        "ECM_START_MILEAGE": "142787000",
        "END_ENGINE_TOTAL_RUNTIME_TIME": "3930.25",
        "VB_BRAKE_COUNT": "401",
        "VB_RUN_TIME": "27070",
        "VB_BRAKE_MILEAGE": "23300",
        "CAN_BUS_START_MILEAGE": "142787000",
        "VB_ENGINE_TIME": "27070",
        "VB_MAX_VELOCITY": "110.00",
        "VB_MIN_ELEVATION": "0",
        "START_FUEL_CONSUMPTION_IDLE": "1936.00",
        "END_IDLE_TIME": "961",
        "VB_AVG_VELOCITY": "44.31",
        "VDR_END_MILEAGE": "139193945",
        "END_ENGINE_RUNTIME_TIME": "3807.25",
        "ECM_END_MILEAGE": "143129640",
        "START_IDLE_TIME": "959",
        "VDR_START_MILEAGE": "138860755",
        "VB_CLUTCH_TIME": "3785",
        "VB_IDLE_TIME": "5950",
        "VB_MIN_VELOCITY": "0.00",
        "VB_MAX_ELEVATION": "0",
        "START_ENGINE_RUNTIME_TIME": "3798.45",
        "CAN_BUS_END_MILEAGE": "143129625",
        "ERROR_GPS": "GPS定位异常",
        "VB_OFFLINE_TIME": "0",
        "VB_IDLE_FUEL_CONSUMPTION": "2.70",
        "VB_BRAKE_TIME": "3354",
        "VB_STOP_TIME": "59330"
      },
      "cycleGasConsumptionKg": "",
      "dataTime": "2019-02-12 00:00:00",
      "did": "A64838039045",
      "endCycleGasKg": "",
      "endFuel": 49531.0,
      "endGasKg": "",
      "endGasL": "",
      "endHydrogen": "",
      "endMileage": 139193945,
      "engineTime": 31680,
      "exceptions": {},
      "fuelConsumption": 90.0,
      "gasConsumptionKg": "",
      "gasConsumptionL": "",
      "gpsMileage": 0,
      "hydrogenConsumption": "",
      "id": "A64838039045",
      "idleFuelConsumption": 4.0,
      "idleTime": 6479,
      "isWork": true,
      "locationEndTime": "2019-02-12 23:59:35",
      "locationStartTime": "2019-02-12 00:29:39",
      "maxElevation": 0,
      "maxVelocity": 100.8,
      "mileage": 333190,
      "mileageSource": "VDR",
      "minElevation": 0,
      "minVelocity": 0.1,
      "offlineTimeInSeconds": 0,
      "perCycleGasConsumptionKg": "",
      "perFuelConsumption": 27.011614994447612,
      "perGasConsumptionKg": "",
      "perGasConsumptionL": "",
      "perHydrogenConsumption": "",
      "perUnchargePower": "",
      "points": 1427,
      "protocol": "ZKC02",
      "province": "江西省",
      "remark": "",
      "rowKey": "00000168dd496000954736fbef227a67868e8bd92d62d02d",
      "runTimeInSeconds": 31680,
      "startCycleGasKg": "",
      "startFuel": 49441.0,
      "startGasKg": "",
      "startGasL": "",
      "startHydrogen": "",
      "startMileage": 138860755,
      "stopTimeInSeconds": 54720,
      "unchargeCount": 0,
      "unchargePower": 0.0,
      "workTimeInSeconds": 31680
    },
    {
      "avgElevation": 0,
      "avgVelocity": 39.52247191011236,
      "brakeCount": "",
      "brakeMileage": "",
      "brakeTime": "",
      "canEndTime": "2019-02-13 23:58:37",
      "canPoints": 6992,
      "canStartTime": "2019-02-13 00:00:00",
      "chargeCount": 0,
      "chargePower": 0.0,
      "city": "萍乡市",
      "clutchCount": "",
      "clutchTime": "",
      "codes": {
        "START_ENGINE_TOTAL_RUNTIME_TIME": "3930.35",
        "VB_AVG_ELEVATION": "0",
        "END_FUEL_CONSUMPTION_IDLE": "1944.50",
        "VB_CLUTCH_COUNT": "640",
        "VB_WORK_TIME": "30468",
        "ECM_START_MILEAGE": "143130295",
        "END_ENGINE_TOTAL_RUNTIME_TIME": "3939.35",
        "VB_BRAKE_COUNT": "433",
        "VB_RUN_TIME": "30468",
        "VB_BRAKE_MILEAGE": "24100",
        "CAN_BUS_START_MILEAGE": "143130250",
        "VB_ENGINE_TIME": "30468",
        "VB_MAX_VELOCITY": "100.00",
        "VB_MIN_ELEVATION": "0",
        "START_FUEL_CONSUMPTION_IDLE": "1940.00",
        "END_IDLE_TIME": "963",
        "VB_AVG_VELOCITY": "41.56",
        "VDR_END_MILEAGE": "139546335",
        "END_ENGINE_RUNTIME_TIME": "3816.25",
        "ECM_END_MILEAGE": "143492030",
        "START_IDLE_TIME": "961",
        "VDR_START_MILEAGE": "139194585",
        "VB_CLUTCH_TIME": "5043",
        "VB_IDLE_TIME": "5907",
        "VB_MIN_VELOCITY": "0.00",
        "VB_MAX_ELEVATION": "0",
        "START_ENGINE_RUNTIME_TIME": "3807.35",
        "CAN_BUS_END_MILEAGE": "143492000",
        "ERROR_GPS": "GPS定位异常",
        "VB_OFFLINE_TIME": "0",
        "VB_IDLE_FUEL_CONSUMPTION": "3.20",
        "VB_BRAKE_TIME": "3424",
        "VB_STOP_TIME": "55932"
      },
      "cycleGasConsumptionKg": "",
      "dataTime": "2019-02-13 00:00:00",
      "did": "A64838039045",
      "endCycleGasKg": "",
      "endFuel": 49689.5,
      "endGasKg": "",
      "endGasL": "",
      "endHydrogen": "",
      "endMileage": 139546335,
      "engineTime": 32040,
      "exceptions": {},
      "fuelConsumption": 121.5,
      "gasConsumptionKg": "",
      "gasConsumptionL": "",
      "gpsMileage": 0,
      "hydrogenConsumption": "",
      "id": "A64838039045",
      "idleFuelConsumption": 4.5,
      "idleTime": 7200,
      "isWork": true,
      "locationEndTime": "2019-02-13 23:58:37",
      "locationStartTime": "2019-02-13 00:00:05",
      "maxElevation": 0,
      "maxVelocity": 96.2,
      "mileage": 351750,
      "mileageSource": "VDR",
      "minElevation": 0,
      "minVelocity": 0.3,
      "offlineTimeInSeconds": 0,
      "perCycleGasConsumptionKg": "",
      "perFuelConsumption": 34.54157782515991,
      "perGasConsumptionKg": "",
      "perGasConsumptionL": "",
      "perHydrogenConsumption": "",
      "perUnchargePower": "",
      "points": 1399,
      "protocol": "ZKC02",
      "province": "江西省",
      "remark": "",
      "rowKey": "00000168e26fbc00954736fbef227a67868e8bd92d62d02d",
      "runTimeInSeconds": 32040,
      "startCycleGasKg": "",
      "startFuel": 49568.0,
      "startGasKg": "",
      "startGasL": "",
      "startHydrogen": "",
      "startMileage": 139194585,
      "stopTimeInSeconds": 54360,
      "unchargeCount": 0,
      "unchargePower": 0.0,
      "workTimeInSeconds": 32040
    },
    {
      "avgElevation": 0,
      "avgVelocity": 44.29774585087937,
      "brakeCount": "",
      "brakeMileage": "",
      "brakeTime": "",
      "canEndTime": "2019-02-14 23:37:56",
      "canPoints": 5827,
      "canStartTime": "2019-02-14 00:27:24",
      "chargeCount": 0,
      "chargePower": 0.0,
      "city": "萍乡市",
      "clutchCount": "",
      "clutchTime": "",
      "codes": {
        "START_ENGINE_TOTAL_RUNTIME_TIME": "3939.45",
        "VB_AVG_ELEVATION": "0",
        "END_FUEL_CONSUMPTION_IDLE": "1947.50",
        "VB_CLUTCH_COUNT": "486",
        "VB_WORK_TIME": "25044",
        "ECM_START_MILEAGE": "143492030",
        "END_ENGINE_TOTAL_RUNTIME_TIME": "3947.40",
        "VB_BRAKE_COUNT": "355",
        "VB_RUN_TIME": "25044",
        "VB_BRAKE_MILEAGE": "23100",
        "CAN_BUS_START_MILEAGE": "143492000",
        "VB_ENGINE_TIME": "25044",
        "VB_MAX_VELOCITY": "100.00",
        "VB_MIN_ELEVATION": "0",
        "START_FUEL_CONSUMPTION_IDLE": "1945.00",
        "END_IDLE_TIME": "964",
        "VB_AVG_VELOCITY": "49.98",
        "VDR_END_MILEAGE": "139894060",
        "END_ENGINE_RUNTIME_TIME": "3824.15",
        "ECM_END_MILEAGE": "143849710",
        "START_IDLE_TIME": "963",
        "VDR_START_MILEAGE": "139546335",
        "VB_CLUTCH_TIME": "2872",
        "VB_IDLE_TIME": "2980",
        "VB_MIN_VELOCITY": "0.00",
        "VB_MAX_ELEVATION": "0",
        "START_ENGINE_RUNTIME_TIME": "3816.30",
        "CAN_BUS_END_MILEAGE": "143849625",
        "ERROR_GPS": "GPS定位异常",
        "VB_OFFLINE_TIME": "0",
        "VB_IDLE_FUEL_CONSUMPTION": "1.50",
        "VB_BRAKE_TIME": "2639",
        "VB_STOP_TIME": "61356"
      },
      "cycleGasConsumptionKg": "",
      "dataTime": "2019-02-14 00:00:00",
      "did": "A64838039045",
      "endCycleGasKg": "",
      "endFuel": 49820.0,
      "endGasKg": "",
      "endGasL": "",
      "endHydrogen": "",
      "endMileage": 139894060,
      "engineTime": 28259,
      "exceptions": {},
      "fuelConsumption": 115.5,
      "gasConsumptionKg": "",
      "gasConsumptionL": "",
      "gpsMileage": 0,
      "hydrogenConsumption": "",
      "id": "A64838039045",
      "idleFuelConsumption": 2.5,
      "idleTime": 4500,
      "isWork": true,
      "locationEndTime": "2019-02-14 23:37:56",
      "locationStartTime": "2019-02-14 00:28:39",
      "maxElevation": 0,
      "maxVelocity": 98.9,
      "mileage": 347725,
      "mileageSource": "VDR",
      "minElevation": 0,
      "minVelocity": 0.2,
      "offlineTimeInSeconds": 0,
      "perCycleGasConsumptionKg": "",
      "perFuelConsumption": 33.21590337191746,
      "perGasConsumptionKg": "",
      "perGasConsumptionL": "",
      "perHydrogenConsumption": "",
      "perUnchargePower": "",
      "points": 1201,
      "protocol": "ZKC02",
      "province": "江西省",
      "remark": "",
      "rowKey": "00000168e7961800954736fbef227a67868e8bd92d62d02d",
      "runTimeInSeconds": 28259,
      "startCycleGasKg": "",
      "startFuel": 49704.5,
      "startGasKg": "",
      "startGasL": "",
      "startHydrogen": "",
      "startMileage": 139546335,
      "stopTimeInSeconds": 58141,
      "unchargeCount": 0,
      "unchargePower": 0.0,
      "workTimeInSeconds": 28259
    },
    {
      "avgElevation": 0,
      "avgVelocity": 39.06166666666667,
      "brakeCount": "",
      "brakeMileage": "",
      "brakeTime": "",
      "canEndTime": "2019-02-15 23:52:55",
      "canPoints": 6998,
      "canStartTime": "2019-02-15 00:06:43",
      "chargeCount": 0,
      "chargePower": 0.0,
      "city": "萍乡市",
      "clutchCount": "",
      "clutchTime": "",
      "codes": {
        "START_ENGINE_TOTAL_RUNTIME_TIME": "3947.45",
        "VB_AVG_ELEVATION": "0",
        "END_FUEL_CONSUMPTION_IDLE": "1951.50",
        "VB_CLUTCH_COUNT": "564",
        "VB_WORK_TIME": "27121",
        "ECM_START_MILEAGE": "143849710",
        "END_ENGINE_TOTAL_RUNTIME_TIME": "3956.60",
        "VB_BRAKE_COUNT": "326",
        "VB_RUN_TIME": "27121",
        "VB_BRAKE_MILEAGE": "21400",
        "CAN_BUS_START_MILEAGE": "143849625",
        "VB_ENGINE_TIME": "27121",
        "VB_MAX_VELOCITY": "100.00",
        "VB_MIN_ELEVATION": "0",
        "START_FUEL_CONSUMPTION_IDLE": "1947.50",
        "END_IDLE_TIME": "966",
        "VB_AVG_VELOCITY": "46.66",
        "VDR_END_MILEAGE": "140245625",
        "END_ENGINE_RUNTIME_TIME": "3833.20",
        "ECM_END_MILEAGE": "144211155",
        "START_IDLE_TIME": "964",
        "VDR_START_MILEAGE": "139894070",
        "VB_CLUTCH_TIME": "3796",
        "VB_IDLE_TIME": "5679",
        "VB_MIN_VELOCITY": "0.00",
        "VB_MAX_ELEVATION": "0",
        "START_ENGINE_RUNTIME_TIME": "3824.20",
        "CAN_BUS_END_MILEAGE": "144211125",
        "ERROR_GPS": "GPS定位异常",
        "VB_OFFLINE_TIME": "0",
        "VB_IDLE_FUEL_CONSUMPTION": "3.50",
        "VB_BRAKE_TIME": "3482",
        "VB_STOP_TIME": "59279"
      },
      "cycleGasConsumptionKg": "",
      "dataTime": "2019-02-15 00:00:00",
      "did": "A64838039045",
      "endCycleGasKg": "",
      "endFuel": 49915.5,
      "endGasKg": "",
      "endGasL": "",
      "endHydrogen": "",
      "endMileage": 140245625,
      "engineTime": 32400,
      "exceptions": {},
      "fuelConsumption": 80.0,
      "gasConsumptionKg": "",
      "gasConsumptionL": "",
      "gpsMileage": 0,
      "hydrogenConsumption": "",
      "id": "A64838039045",
      "idleFuelConsumption": 4.0,
      "idleTime": 6479,
      "isWork": true,
      "locationEndTime": "2019-02-15 23:52:55",
      "locationStartTime": "2019-02-15 00:07:58",
      "maxElevation": 0,
      "maxVelocity": 92.8,
      "mileage": 351555,
      "mileageSource": "VDR",
      "minElevation": 0,
      "minVelocity": 0.1,
      "offlineTimeInSeconds": 0,
      "perCycleGasConsumptionKg": "",
      "perFuelConsumption": 22.756041017763934,
      "perGasConsumptionKg": "",
      "perGasConsumptionL": "",
      "perHydrogenConsumption": "",
      "perUnchargePower": "",
      "points": 1410,
      "protocol": "ZKC02",
      "province": "江西省",
      "remark": "",
      "rowKey": "00000168ecbc7400954736fbef227a67868e8bd92d62d02d",
      "runTimeInSeconds": 32400,
      "startCycleGasKg": "",
      "startFuel": 49835.5,
      "startGasKg": "",
      "startGasL": "",
      "startHydrogen": "",
      "startMileage": 139894070,
      "stopTimeInSeconds": 54000,
      "unchargeCount": 0,
      "unchargePower": 0.0,
      "workTimeInSeconds": 32400
    },
    {
      "avgElevation": 0,
      "avgVelocity": 40.1562028324609,
      "brakeCount": "",
      "brakeMileage": "",
      "brakeTime": "",
      "canEndTime": "2019-02-16 23:50:48",
      "canPoints": 6311,
      "canStartTime": "2019-02-16 00:21:43",
      "chargeCount": 0,
      "chargePower": 0.0,
      "city": "萍乡市",
      "clutchCount": "",
      "clutchTime": "",
      "codes": {
        "START_ENGINE_TOTAL_RUNTIME_TIME": "3956.70",
        "VB_AVG_ELEVATION": "0",
        "END_FUEL_CONSUMPTION_IDLE": "1956.50",
        "VB_CLUTCH_COUNT": "552",
        "VB_WORK_TIME": "27966",
        "ECM_START_MILEAGE": "144211155",
        "END_ENGINE_TOTAL_RUNTIME_TIME": "3965.45",
        "VB_BRAKE_COUNT": "346",
        "VB_RUN_TIME": "27966",
        "VB_BRAKE_MILEAGE": "25200",
        "CAN_BUS_START_MILEAGE": "144211125",
        "VB_ENGINE_TIME": "27966",
        "VB_MAX_VELOCITY": "100.00",
        "VB_MIN_ELEVATION": "0",
        "START_FUEL_CONSUMPTION_IDLE": "1952.00",
        "END_IDLE_TIME": "968",
        "VB_AVG_VELOCITY": "44.71",
        "VDR_END_MILEAGE": "140592965",
        "END_ENGINE_RUNTIME_TIME": "3841.95",
        "ECM_END_MILEAGE": "144568390",
        "START_IDLE_TIME": "966",
        "VDR_START_MILEAGE": "140245625",
        "VB_CLUTCH_TIME": "3680",
        "VB_IDLE_TIME": "6290",
        "VB_MIN_VELOCITY": "0.00",
        "VB_MAX_ELEVATION": "0",
        "START_ENGINE_RUNTIME_TIME": "3833.30",
        "CAN_BUS_END_MILEAGE": "144568375",
        "ERROR_GPS": "GPS定位异常",
        "VB_OFFLINE_TIME": "0",
        "VB_IDLE_FUEL_CONSUMPTION": "3.60",
        "VB_BRAKE_TIME": "3394",
        "VB_STOP_TIME": "58434"
      },
      "cycleGasConsumptionKg": "",
      "dataTime": "2019-02-16 00:00:00",
      "did": "A64838039045",
      "endCycleGasKg": "",
      "endFuel": 50069.5,
      "endGasKg": "",
      "endGasL": "",
      "endHydrogen": "",
      "endMileage": 140592965,
      "engineTime": 31139,
      "exceptions": {},
      "fuelConsumption": 115.0,
      "gasConsumptionKg": "",
      "gasConsumptionL": "",
      "gpsMileage": 0,
      "hydrogenConsumption": "",
      "id": "A64838039045",
      "idleFuelConsumption": 4.5,
      "idleTime": 7200,
      "isWork": true,
      "locationEndTime": "2019-02-16 23:50:48",
      "locationStartTime": "2019-02-16 00:22:58",
      "maxElevation": 0,
      "maxVelocity": 98.2,
      "mileage": 347340,
      "mileageSource": "VDR",
      "minElevation": 0,
      "minVelocity": 0.2,
      "offlineTimeInSeconds": 0,
      "perCycleGasConsumptionKg": "",
      "perFuelConsumption": 33.108769505383776,
      "perGasConsumptionKg": "",
      "perGasConsumptionL": "",
      "perHydrogenConsumption": "",
      "perUnchargePower": "",
      "points": 1364,
      "protocol": "ZKC02",
      "province": "江西省",
      "remark": "",
      "rowKey": "00000168f1e2d000954736fbef227a67868e8bd92d62d02d",
      "runTimeInSeconds": 31139,
      "startCycleGasKg": "",
      "startFuel": 49954.5,
      "startGasKg": "",
      "startGasL": "",
      "startHydrogen": "",
      "startMileage": 140245625,
      "stopTimeInSeconds": 55261,
      "unchargeCount": 0,
      "unchargePower": 0.0,
      "workTimeInSeconds": 31139
    },
    {
      "avgElevation": 0,
      "avgVelocity": 5.68076923076923,
      "brakeCount": "",
      "brakeMileage": "",
      "brakeTime": "",
      "canEndTime": "2019-02-17 23:43:28",
      "canPoints": 1280,
      "canStartTime": "2019-02-17 00:10:03",
      "chargeCount": 0,
      "chargePower": 0.0,
      "city": "萍乡市",
      "clutchCount": "",
      "clutchTime": "",
      "codes": {
        "START_ENGINE_TOTAL_RUNTIME_TIME": "3965.50",
        "VB_AVG_ELEVATION": "0",
        "END_FUEL_CONSUMPTION_IDLE": "1960.00",
        "VB_CLUTCH_COUNT": "86",
        "VB_WORK_TIME": "5084",
        "ECM_START_MILEAGE": "144568390",
        "END_ENGINE_TOTAL_RUNTIME_TIME": "3966.80",
        "VB_BRAKE_COUNT": "36",
        "VB_RUN_TIME": "5084",
        "VB_BRAKE_MILEAGE": "400",
        "CAN_BUS_START_MILEAGE": "144568375",
        "VB_ENGINE_TIME": "5084",
        "VB_MAX_VELOCITY": "70.00",
        "VB_MIN_ELEVATION": "0",
        "START_FUEL_CONSUMPTION_IDLE": "1956.50",
        "END_IDLE_TIME": "969",
        "VB_AVG_VELOCITY": "5.23",
        "VDR_END_MILEAGE": "140600350",
        "END_ENGINE_RUNTIME_TIME": "3843.25",
        "ECM_END_MILEAGE": "144575920",
        "START_IDLE_TIME": "968",
        "VDR_START_MILEAGE": "140592965",
        "VB_CLUTCH_TIME": "767",
        "VB_IDLE_TIME": "3561",
        "VB_MIN_VELOCITY": "0.00",
        "VB_MAX_ELEVATION": "0",
        "START_ENGINE_RUNTIME_TIME": "3841.95",
        "CAN_BUS_END_MILEAGE": "144575875",
        "VB_OFFLINE_TIME": "0",
        "VB_IDLE_FUEL_CONSUMPTION": "3.00",
        "VB_BRAKE_TIME": "193",
        "VB_STOP_TIME": "81316"
      },
      "cycleGasConsumptionKg": "",
      "dataTime": "2019-02-17 00:00:00",
      "did": "A64838039045",
      "endCycleGasKg": "",
      "endFuel": 50096.0,
      "endGasKg": "",
      "endGasL": "",
      "endHydrogen": "",
      "endMileage": 140600350,
      "engineTime": 4680,
      "exceptions": {},
      "fuelConsumption": 1.0,
      "gasConsumptionKg": "",
      "gasConsumptionL": "",
      "gpsMileage": 0,
      "hydrogenConsumption": "",
      "id": "A64838039045",
      "idleFuelConsumption": 3.5,
      "idleTime": 3600,
      "isWork": true,
      "locationEndTime": "2019-02-17 23:43:28",
      "locationStartTime": "2019-02-17 00:10:06",
      "maxElevation": 0,
      "maxVelocity": 56.0,
      "mileage": 7385,
      "mileageSource": "VDR",
      "minElevation": 0,
      "minVelocity": 0.2,
      "offlineTimeInSeconds": 0,
      "perCycleGasConsumptionKg": "",
      "perFuelConsumption": 13.540961408259987,
      "perGasConsumptionKg": "",
      "perGasConsumptionL": "",
      "perHydrogenConsumption": "",
      "perUnchargePower": "",
      "points": 286,
      "protocol": "ZKC02",
      "province": "江西省",
      "remark": "",
      "rowKey": "00000168f7092c00954736fbef227a67868e8bd92d62d02d",
      "runTimeInSeconds": 4680,
      "startCycleGasKg": "",
      "startFuel": 50095.0,
      "startGasKg": "",
      "startGasL": "",
      "startHydrogen": "",
      "startMileage": 140592965,
      "stopTimeInSeconds": 81720,
      "unchargeCount": 0,
      "unchargePower": 0.0,
      "workTimeInSeconds": 4680
    },
    {
      "avgElevation": 0,
      "avgVelocity": 38.68150289017341,
      "brakeCount": "",
      "brakeMileage": "",
      "brakeTime": "",
      "canEndTime": "2019-02-18 23:53:07",
      "canPoints": 6435,
      "canStartTime": "2019-02-18 00:12:15",
      "chargeCount": 0,
      "chargePower": 0.0,
      "city": "萍乡市",
      "clutchCount": "",
      "clutchTime": "",
      "codes": {
        "START_ENGINE_TOTAL_RUNTIME_TIME": "3966.90",
        "VB_AVG_ELEVATION": "0",
        "END_FUEL_CONSUMPTION_IDLE": "1964.50",
        "VB_CLUTCH_COUNT": "622",
        "VB_WORK_TIME": "29470",
        "ECM_START_MILEAGE": "144575920",
        "END_ENGINE_TOTAL_RUNTIME_TIME": "3975.95",
        "VB_BRAKE_COUNT": "346",
        "VB_RUN_TIME": "29470",
        "VB_BRAKE_MILEAGE": "24500",
        "CAN_BUS_START_MILEAGE": "144575875",
        "VB_ENGINE_TIME": "29470",
        "VB_MAX_VELOCITY": "100.00",
        "VB_MIN_ELEVATION": "0",
        "START_FUEL_CONSUMPTION_IDLE": "1960.00",
        "END_IDLE_TIME": "971",
        "VB_AVG_VELOCITY": "40.87",
        "VDR_END_MILEAGE": "140934945",
        "END_ENGINE_RUNTIME_TIME": "3852.00",
        "ECM_END_MILEAGE": "144920000",
        "START_IDLE_TIME": "969",
        "VDR_START_MILEAGE": "140600350",
        "VB_CLUTCH_TIME": "4404",
        "VB_IDLE_TIME": "6782",
        "VB_MIN_VELOCITY": "0.00",
        "VB_MAX_ELEVATION": "0",
        "START_ENGINE_RUNTIME_TIME": "3843.35",
        "CAN_BUS_END_MILEAGE": "144920000",
        "ERROR_GPS": "GPS定位异常",
        "VB_OFFLINE_TIME": "0",
        "VB_IDLE_FUEL_CONSUMPTION": "4.10",
        "VB_BRAKE_TIME": "4103",
        "VB_STOP_TIME": "56930"
      },
      "cycleGasConsumptionKg": "",
      "dataTime": "2019-02-18 00:00:00",
      "did": "A64838039045",
      "endCycleGasKg": "",
      "endFuel": 50229.0,
      "endGasKg": "",
      "endGasL": "",
      "endHydrogen": "",
      "endMileage": 140934945,
      "engineTime": 31140,
      "exceptions": {},
      "fuelConsumption": 132.0,
      "gasConsumptionKg": "",
      "gasConsumptionL": "",
      "gpsMileage": 0,
      "hydrogenConsumption": "",
      "id": "A64838039045",
      "idleFuelConsumption": 4.5,
      "idleTime": 6660,
      "isWork": true,
      "locationEndTime": "2019-02-18 23:53:07",
      "locationStartTime": "2019-02-18 00:13:30",
      "maxElevation": 0,
      "maxVelocity": 98.5,
      "mileage": 334595,
      "mileageSource": "VDR",
      "minElevation": 0,
      "minVelocity": 0.2,
      "offlineTimeInSeconds": 0,
      "perCycleGasConsumptionKg": "",
      "perFuelConsumption": 39.45067917930633,
      "perGasConsumptionKg": "",
      "perGasConsumptionL": "",
      "perHydrogenConsumption": "",
      "perUnchargePower": "",
      "points": 1307,
      "protocol": "ZKC02",
      "province": "江西省",
      "remark": "",
      "rowKey": "00000168fc2f8800954736fbef227a67868e8bd92d62d02d",
      "runTimeInSeconds": 31140,
      "startCycleGasKg": "",
      "startFuel": 50097.0,
      "startGasKg": "",
      "startGasL": "",
      "startHydrogen": "",
      "startMileage": 140600350,
      "stopTimeInSeconds": 55260,
      "unchargeCount": 0,
      "unchargePower": 0.0,
      "workTimeInSeconds": 31140
    },
    {
      "avgElevation": 0,
      "avgVelocity": 15.155555555555555,
      "brakeCount": "",
      "brakeMileage": "",
      "brakeTime": "",
      "canEndTime": "2019-02-19 23:41:38",
      "canPoints": 702,
      "canStartTime": "2019-02-19 00:22:03",
      "chargeCount": 0,
      "chargePower": 0.0,
      "city": "萍乡市",
      "clutchCount": "",
      "clutchTime": "",
      "codes": {
        "START_ENGINE_TOTAL_RUNTIME_TIME": "3976.00",
        "VB_AVG_ELEVATION": "0",
        "END_FUEL_CONSUMPTION_IDLE": "1965.50",
        "VB_CLUTCH_COUNT": "55",
        "VB_WORK_TIME": "1801",
        "ECM_START_MILEAGE": "144920000",
        "END_ENGINE_TOTAL_RUNTIME_TIME": "3976.40",
        "VB_BRAKE_COUNT": "32",
        "VB_RUN_TIME": "1801",
        "VB_BRAKE_MILEAGE": "1000",
        "CAN_BUS_START_MILEAGE": "144920000",
        "VB_ENGINE_TIME": "1801",
        "VB_MAX_VELOCITY": "80.00",
        "VB_MIN_ELEVATION": "0",
        "START_FUEL_CONSUMPTION_IDLE": "1964.50",
        "END_IDLE_TIME": "971",
        "VB_AVG_VELOCITY": "13.63",
        "VDR_END_MILEAGE": "140941765",
        "END_ENGINE_RUNTIME_TIME": "3852.55",
        "ECM_END_MILEAGE": "144927005",
        "START_IDLE_TIME": "971",
        "VDR_START_MILEAGE": "140934945",
        "VB_CLUTCH_TIME": "602",
        "VB_IDLE_TIME": "769",
        "VB_MIN_VELOCITY": "0.00",
        "VB_MAX_ELEVATION": "0",
        "START_ENGINE_RUNTIME_TIME": "3852.10",
        "CAN_BUS_END_MILEAGE": "144927000",
        "VB_OFFLINE_TIME": "0",
        "VB_IDLE_FUEL_CONSUMPTION": "1.10",
        "VB_BRAKE_TIME": "126",
        "VB_STOP_TIME": "84599"
      },
      "cycleGasConsumptionKg": "",
      "dataTime": "2019-02-19 00:00:00",
      "did": "A64838039045",
      "endCycleGasKg": "",
      "endFuel": 50235.0,
      "endGasKg": "",
      "endGasL": "",
      "endHydrogen": "",
      "endMileage": 140941765,
      "engineTime": 1620,
      "exceptions": {},
      "fuelConsumption": 3.0,
      "gasConsumptionKg": "",
      "gasConsumptionL": "",
      "gpsMileage": 0,
      "hydrogenConsumption": "",
      "id": "A64838039045",
      "idleFuelConsumption": 1.0,
      "idleTime": 540,
      "isWork": true,
      "locationEndTime": "2019-02-19 23:41:38",
      "locationStartTime": "2019-02-19 00:23:18",
      "maxElevation": 0,
      "maxVelocity": 70.3,
      "mileage": 6820,
      "mileageSource": "VDR",
      "minElevation": 0,
      "minVelocity": 1.7,
      "offlineTimeInSeconds": 0,
      "perCycleGasConsumptionKg": "",
      "perFuelConsumption": 43.988269794721404,
      "perGasConsumptionKg": "",
      "perGasConsumptionL": "",
      "perHydrogenConsumption": "",
      "perUnchargePower": "",
      "points": 144,
      "protocol": "ZKC02",
      "province": "江西省",
      "remark": "",
      "rowKey": "000001690155e400954736fbef227a67868e8bd92d62d02d",
      "runTimeInSeconds": 1620,
      "startCycleGasKg": "",
      "startFuel": 50232.0,
      "startGasKg": "",
      "startGasL": "",
      "startHydrogen": "",
      "startMileage": 140934945,
      "stopTimeInSeconds": 84780,
      "unchargeCount": 0,
      "unchargePower": 0.0,
      "workTimeInSeconds": 1620
    }
  ],
  "data": "",
  "info": "",
  "list": "",
  "success": true,
  "summary": "",
  "texts": "",
  "totalCount": 13,
  "url": ""
}